ply2atti.py
ply2atti-0.2.4.dist-info/DESCRIPTION.rst
ply2atti-0.2.4.dist-info/METADATA
ply2atti-0.2.4.dist-info/RECORD
ply2atti-0.2.4.dist-info/WHEEL
ply2atti-0.2.4.dist-info/entry_points.txt
ply2atti-0.2.4.dist-info/metadata.json
ply2atti-0.2.4.dist-info/top_level.txt
