Metadata-Version: 2.0
Name: ply2atti
Version: 0.2.4
Summary: Script for extraction of attitudes from 3d models using meshlab's mesh painting tool
Home-page: https://github.com/endarthur/ply2atti
Author: Arthur Endlein
Author-email: endarthur@gmail.com
License: MIT
Keywords: geology attitudes meshlab
Platform: UNKNOWN
Classifier: Development Status :: 3 - Alpha
Classifier: Topic :: Utilities
Classifier: License :: OSI Approved :: MIT License
Requires-Dist: XlsxWriter
Requires-Dist: networkx
Requires-Dist: numpy
